iotile_analytics/__init__.py
iotile_analytics/offline/__init__.py
iotile_analytics/offline/database.py
iotile_analytics/offline/integration.py
iotile_analytics/offline/report.py
iotile_analytics/offline/table_descriptions/__init__.py
iotile_analytics/offline/table_descriptions/event_index.py
iotile_analytics/offline/table_descriptions/info.py
iotile_analytics/offline/table_descriptions/properties.py
iotile_analytics/offline/table_descriptions/stream.py
iotile_analytics_offline-0.3.0.dist-info/METADATA
iotile_analytics_offline-0.3.0.dist-info/WHEEL
iotile_analytics_offline-0.3.0.dist-info/entry_points.txt
iotile_analytics_offline-0.3.0.dist-info/top_level.txt
iotile_analytics_offline-0.3.0.dist-info/RECORD
